{
	"info": {},
	"license": {},
	"images": [
		{
			"id": "1583398575542",
			"width": 512,
			"height": 512,
			"file_name": "1583398575542-588.jpg",
			"data_captured": 1583398576.50904
		}
	],
	"annotations": [
		{
			"id": "1583398575542",
			"text": [
				{
					"text_id": "1583398575542-0-0",
					"contents": "탠"
				},
				{
					"text_id": "1583398575542-0-1",
					"contents": "좨"
				},
				{
					"text_id": "1583398575542-0-2",
					"contents": "옷"
				},
				{
					"text_id": "1583398575542-0-6",
					"contents": "곽"
				},
				{
					"text_id": "1583398575542-0-7",
					"contents": "찻"
				},
				{
					"text_id": "1583398575542-0-8",
					"contents": "방"
				},
				{
					"text_id": "1583398575542-0-9",
					"contents": "칠"
				},
				{
					"text_id": "1583398575542-0-10",
					"contents": "증"
				},
				{
					"text_id": "1583398575542-0-11",
					"contents": "티"
				},
				{
					"text_id": "1583398575542-0-12",
					"contents": "랍"
				},
				{
					"text_id": "1583398575542-0-13",
					"contents": "윈"
				},
				{
					"text_id": "1583398575542-0-14",
					"contents": "쏘"
				},
				{
					"text_id": "1583398575542-0-15",
					"contents": "매"
				},
				{
					"text_id": "1583398575542-1-2",
					"contents": "차"
				},
				{
					"text_id": "1583398575542-1-3",
					"contents": "쉬"
				},
				{
					"text_id": "1583398575542-1-4",
					"contents": "추"
				},
				{
					"text_id": "1583398575542-1-6",
					"contents": "욱"
				},
				{
					"text_id": "1583398575542-1-9",
					"contents": "쩌"
				},
				{
					"text_id": "1583398575542-1-10",
					"contents": "흥"
				},
				{
					"text_id": "1583398575542-1-12",
					"contents": "섀"
				},
				{
					"text_id": "1583398575542-1-13",
					"contents": "삼"
				},
				{
					"text_id": "1583398575542-1-15",
					"contents": "b"
				},
				{
					"text_id": "1583398575542-1-16",
					"contents": "축"
				},
				{
					"text_id": "1583398575542-2-0",
					"contents": "쉬"
				},
				{
					"text_id": "1583398575542-2-1",
					"contents": "핸"
				},
				{
					"text_id": "1583398575542-2-2",
					"contents": "들"
				},
				{
					"text_id": "1583398575542-2-3",
					"contents": "붐"
				},
				{
					"text_id": "1583398575542-2-4",
					"contents": "7"
				},
				{
					"text_id": "1583398575542-2-5",
					"contents": "닐"
				},
				{
					"text_id": "1583398575542-2-7",
					"contents": "웅"
				},
				{
					"text_id": "1583398575542-2-9",
					"contents": "험"
				},
				{
					"text_id": "1583398575542-2-10",
					"contents": "천"
				},
				{
					"text_id": "1583398575542-2-11",
					"contents": "듦"
				},
				{
					"text_id": "1583398575542-2-12",
					"contents": "딸"
				},
				{
					"text_id": "1583398575542-2-13",
					"contents": "딩"
				},
				{
					"text_id": "1583398575542-3-0",
					"contents": "쨔"
				},
				{
					"text_id": "1583398575542-3-3",
					"contents": "륵"
				},
				{
					"text_id": "1583398575542-3-4",
					"contents": "산"
				},
				{
					"text_id": "1583398575542-4-0",
					"contents": "률"
				},
				{
					"text_id": "1583398575542-4-1",
					"contents": "영"
				},
				{
					"text_id": "1583398575542-4-3",
					"contents": "칠"
				},
				{
					"text_id": "1583398575542-4-4",
					"contents": "쌍"
				},
				{
					"text_id": "1583398575542-4-5",
					"contents": "난"
				},
				{
					"text_id": "1583398575542-4-6",
					"contents": "빗"
				},
				{
					"text_id": "1583398575542-4-8",
					"contents": "승"
				},
				{
					"text_id": "1583398575542-4-9",
					"contents": "먼"
				},
				{
					"text_id": "1583398575542-4-10",
					"contents": "주"
				},
				{
					"text_id": "1583398575542-4-11",
					"contents": "y"
				},
				{
					"text_id": "1583398575542-4-12",
					"contents": "류"
				},
				{
					"text_id": "1583398575542-4-14",
					"contents": "죤"
				},
				{
					"text_id": "1583398575542-5-0",
					"contents": "봉"
				},
				{
					"text_id": "1583398575542-5-1",
					"contents": "배"
				},
				{
					"text_id": "1583398575542-5-2",
					"contents": "겸"
				},
				{
					"text_id": "1583398575542-5-3",
					"contents": "넬"
				},
				{
					"text_id": "1583398575542-5-4",
					"contents": "린"
				},
				{
					"text_id": "1583398575542-5-7",
					"contents": "찬"
				},
				{
					"text_id": "1583398575542-5-8",
					"contents": "퀼"
				},
				{
					"text_id": "1583398575542-5-10",
					"contents": "떠"
				},
				{
					"text_id": "1583398575542-6-1",
					"contents": "명"
				},
				{
					"text_id": "1583398575542-6-2",
					"contents": "젝"
				},
				{
					"text_id": "1583398575542-6-3",
					"contents": "앎"
				},
				{
					"text_id": "1583398575542-6-4",
					"contents": "cn"
				},
				{
					"text_id": "1583398575542-6-5",
					"contents": "cs"
				},
				{
					"text_id": "1583398575542-6-6",
					"contents": "cz"
				},
				{
					"text_id": "1583398575542-6-8",
					"contents": "틀"
				},
				{
					"text_id": "1583398575542-6-9",
					"contents": "씩"
				},
				{
					"text_id": "1583398575542-6-11",
					"contents": "r"
				},
				{
					"text_id": "1583398575542-7-0",
					"contents": "윈"
				},
				{
					"text_id": "1583398575542-7-1",
					"contents": "p"
				},
				{
					"text_id": "1583398575542-7-2",
					"contents": "잔"
				},
				{
					"text_id": "1583398575542-7-3",
					"contents": "창"
				},
				{
					"text_id": "1583398575542-7-5",
					"contents": "툰"
				},
				{
					"text_id": "1583398575542-7-9",
					"contents": "렛"
				},
				{
					"text_id": "1583398575542-7-11",
					"contents": "플"
				},
				{
					"text_id": "1583398575542-7-12",
					"contents": "형"
				},
				{
					"text_id": "1583398575542-7-13",
					"contents": "킴"
				},
				{
					"text_id": "1583398575542-8-4",
					"contents": "퀼"
				},
				{
					"text_id": "1583398575542-8-5",
					"contents": "단"
				},
				{
					"text_id": "1583398575542-8-6",
					"contents": "푸"
				},
				{
					"text_id": "1583398575542-8-7",
					"contents": "율"
				},
				{
					"text_id": "1583398575542-8-8",
					"contents": "채"
				},
				{
					"text_id": "1583398575542-8-9",
					"contents": "싼"
				},
				{
					"text_id": "1583398575542-8-12",
					"contents": "듣"
				},
				{
					"text_id": "1583398575542-8-13",
					"contents": "옷"
				},
				{
					"text_id": "1583398575542-8-14",
					"contents": "린"
				},
				{
					"text_id": "1583398575542-8-15",
					"contents": "만"
				},
				{
					"text_id": "1583398575542-8-19",
					"contents": "롭"
				},
				{
					"text_id": "1583398575542-8-22",
					"contents": "무"
				},
				{
					"text_id": "1583398575542-8-23",
					"contents": "툴"
				},
				{
					"text_id": "1583398575542-9-0",
					"contents": "평"
				},
				{
					"text_id": "1583398575542-9-1",
					"contents": "잠"
				},
				{
					"text_id": "1583398575542-9-3",
					"contents": "끌"
				},
				{
					"text_id": "1583398575542-9-4",
					"contents": "듬"
				},
				{
					"text_id": "1583398575542-9-6",
					"contents": "웬"
				},
				{
					"text_id": "1583398575542-9-7",
					"contents": "쵸"
				},
				{
					"text_id": "1583398575542-9-8",
					"contents": "렝"
				},
				{
					"text_id": "1583398575542-9-10",
					"contents": "혁"
				},
				{
					"text_id": "1583398575542-9-11",
					"contents": "캉"
				},
				{
					"text_id": "1583398575542-9-12",
					"contents": "령"
				},
				{
					"text_id": "1583398575542-9-14",
					"contents": "렁"
				},
				{
					"text_id": "1583398575542-9-15",
					"contents": "전"
				},
				{
					"text_id": "1583398575542-9-17",
					"contents": "녕"
				},
				{
					"text_id": "1583398575542-9-18",
					"contents": "넛"
				},
				{
					"text_id": "1583398575542-9-20",
					"contents": "으"
				},
				{
					"text_id": "1583398575542-9-21",
					"contents": "ct"
				},
				{
					"text_id": "1583398575542-9-22",
					"contents": "젤"
				},
				{
					"text_id": "1583398575542-9-23",
					"contents": "웰"
				},
				{
					"text_id": "1583398575542-9-24",
					"contents": "첫"
				},
				{
					"text_id": "1583398575542-9-25",
					"contents": "국"
				},
				{
					"text_id": "1583398575542-10-0",
					"contents": "퍼"
				},
				{
					"text_id": "1583398575542-10-1",
					"contents": "근"
				},
				{
					"text_id": "1583398575542-10-2",
					"contents": "팍"
				},
				{
					"text_id": "1583398575542-10-3",
					"contents": "글"
				},
				{
					"text_id": "1583398575542-10-4",
					"contents": "석"
				},
				{
					"text_id": "1583398575542-10-5",
					"contents": "늘"
				},
				{
					"text_id": "1583398575542-10-6",
					"contents": "뮌"
				},
				{
					"text_id": "1583398575542-10-7",
					"contents": "살"
				},
				{
					"text_id": "1583398575542-10-8",
					"contents": "른"
				},
				{
					"text_id": "1583398575542-10-9",
					"contents": "툴"
				},
				{
					"text_id": "1583398575542-10-10",
					"contents": "물"
				},
				{
					"text_id": "1583398575542-10-12",
					"contents": "꽃"
				},
				{
					"text_id": "1583398575542-10-18",
					"contents": "좨"
				},
				{
					"text_id": "1583398575542-11-0",
					"contents": "갱"
				},
				{
					"text_id": "1583398575542-11-1",
					"contents": "거"
				},
				{
					"text_id": "1583398575542-11-2",
					"contents": "헤"
				},
				{
					"text_id": "1583398575542-11-3",
					"contents": "채"
				},
				{
					"text_id": "1583398575542-11-4",
					"contents": "스"
				},
				{
					"text_id": "1583398575542-11-6",
					"contents": "덤"
				},
				{
					"text_id": "1583398575542-12-1",
					"contents": "샛"
				},
				{
					"text_id": "1583398575542-12-2",
					"contents": "곱"
				},
				{
					"text_id": "1583398575542-12-3",
					"contents": "육"
				},
				{
					"text_id": "1583398575542-12-4",
					"contents": "욥"
				},
				{
					"text_id": "1583398575542-12-5",
					"contents": "젬"
				},
				{
					"text_id": "1583398575542-12-6",
					"contents": "펜"
				},
				{
					"text_id": "1583398575542-12-8",
					"contents": "솜"
				},
				{
					"text_id": "1583398575542-12-9",
					"contents": "쇼"
				},
				{
					"text_id": "1583398575542-12-10",
					"contents": "퀸"
				},
				{
					"text_id": "1583398575542-12-11",
					"contents": "몰"
				},
				{
					"text_id": "1583398575542-12-13",
					"contents": "l"
				},
				{
					"text_id": "1583398575542-12-14",
					"contents": "거"
				},
				{
					"text_id": "1583398575542-12-15",
					"contents": "헴"
				},
				{
					"text_id": "1583398575542-13-0",
					"contents": "cx"
				},
				{
					"text_id": "1583398575542-13-3",
					"contents": "정"
				},
				{
					"text_id": "1583398575542-13-5",
					"contents": "cb"
				},
				{
					"text_id": "1583398575542-13-7",
					"contents": "넛"
				},
				{
					"text_id": "1583398575542-13-8",
					"contents": "드"
				},
				{
					"text_id": "1583398575542-13-11",
					"contents": "해"
				},
				{
					"text_id": "1583398575542-13-12",
					"contents": "쟉"
				},
				{
					"text_id": "1583398575542-13-14",
					"contents": "뫼"
				},
				{
					"text_id": "1583398575542-13-16",
					"contents": "엉"
				}
			],
			"bbox": [
				{
					"bbox_id": "1583398575542-0-0",
					"contents": [
						54,
						15,
						36,
						26
					]
				},
				{
					"bbox_id": "1583398575542-0-1",
					"contents": [
						88,
						15,
						32,
						26
					]
				},
				{
					"bbox_id": "1583398575542-0-2",
					"contents": [
						117,
						15,
						27,
						26
					]
				},
				{
					"bbox_id": "1583398575542-0-6",
					"contents": [
						218,
						15,
						19,
						26
					]
				},
				{
					"bbox_id": "1583398575542-0-7",
					"contents": [
						241,
						15,
						27,
						26
					]
				},
				{
					"bbox_id": "1583398575542-0-8",
					"contents": [
						271,
						15,
						32,
						26
					]
				},
				{
					"bbox_id": "1583398575542-0-9",
					"contents": [
						297,
						15,
						21,
						26
					]
				},
				{
					"bbox_id": "1583398575542-0-10",
					"contents": [
						326,
						15,
						36,
						26
					]
				},
				{
					"bbox_id": "1583398575542-0-11",
					"contents": [
						357,
						15,
						27,
						26
					]
				},
				{
					"bbox_id": "1583398575542-0-12",
					"contents": [
						387,
						15,
						32,
						26
					]
				},
				{
					"bbox_id": "1583398575542-0-13",
					"contents": [
						416,
						15,
						26,
						26
					]
				},
				{
					"bbox_id": "1583398575542-0-14",
					"contents": [
						445,
						15,
						33,
						26
					]
				},
				{
					"bbox_id": "1583398575542-0-15",
					"contents": [
						476,
						15,
						28,
						26
					]
				},
				{
					"bbox_id": "1583398575542-1-2",
					"contents": [
						215,
						35,
						18,
						20
					]
				},
				{
					"bbox_id": "1583398575542-1-3",
					"contents": [
						232,
						35,
						17,
						20
					]
				},
				{
					"bbox_id": "1583398575542-1-4",
					"contents": [
						251,
						35,
						21,
						20
					]
				},
				{
					"bbox_id": "1583398575542-1-6",
					"contents": [
						292,
						35,
						22,
						20
					]
				},
				{
					"bbox_id": "1583398575542-1-9",
					"contents": [
						354,
						35,
						20,
						20
					]
				},
				{
					"bbox_id": "1583398575542-1-10",
					"contents": [
						374,
						35,
						20,
						20
					]
				},
				{
					"bbox_id": "1583398575542-1-12",
					"contents": [
						412,
						35,
						17,
						20
					]
				},
				{
					"bbox_id": "1583398575542-1-13",
					"contents": [
						429,
						35,
						17,
						20
					]
				},
				{
					"bbox_id": "1583398575542-1-15",
					"contents": [
						468,
						35,
						20,
						20
					]
				},
				{
					"bbox_id": "1583398575542-1-16",
					"contents": [
						488,
						35,
						21,
						20
					]
				},
				{
					"bbox_id": "1583398575542-2-0",
					"contents": [
						152,
						53,
						27,
						25
					]
				},
				{
					"bbox_id": "1583398575542-2-1",
					"contents": [
						178,
						53,
						24,
						25
					]
				},
				{
					"bbox_id": "1583398575542-2-2",
					"contents": [
						200,
						53,
						21,
						25
					]
				},
				{
					"bbox_id": "1583398575542-2-3",
					"contents": [
						224,
						53,
						26,
						25
					]
				},
				{
					"bbox_id": "1583398575542-2-4",
					"contents": [
						252,
						53,
						30,
						25
					]
				},
				{
					"bbox_id": "1583398575542-2-5",
					"contents": [
						279,
						53,
						25,
						25
					]
				},
				{
					"bbox_id": "1583398575542-2-7",
					"contents": [
						330,
						53,
						27,
						25
					]
				},
				{
					"bbox_id": "1583398575542-2-9",
					"contents": [
						372,
						53,
						21,
						25
					]
				},
				{
					"bbox_id": "1583398575542-2-10",
					"contents": [
						395,
						53,
						25,
						25
					]
				},
				{
					"bbox_id": "1583398575542-2-11",
					"contents": [
						420,
						53,
						24,
						25
					]
				},
				{
					"bbox_id": "1583398575542-2-12",
					"contents": [
						450,
						53,
						36,
						25
					]
				},
				{
					"bbox_id": "1583398575542-2-13",
					"contents": [
						481,
						53,
						27,
						25
					]
				},
				{
					"bbox_id": "1583398575542-3-0",
					"contents": [
						79,
						70,
						25,
						23
					]
				},
				{
					"bbox_id": "1583398575542-3-3",
					"contents": [
						146,
						70,
						20,
						23
					]
				},
				{
					"bbox_id": "1583398575542-3-4",
					"contents": [
						166,
						70,
						20,
						23
					]
				},
				{
					"bbox_id": "1583398575542-4-0",
					"contents": [
						68,
						86,
						36,
						28
					]
				},
				{
					"bbox_id": "1583398575542-4-1",
					"contents": [
						99,
						86,
						26,
						28
					]
				},
				{
					"bbox_id": "1583398575542-4-3",
					"contents": [
						159,
						86,
						23,
						28
					]
				},
				{
					"bbox_id": "1583398575542-4-4",
					"contents": [
						183,
						86,
						25,
						28
					]
				},
				{
					"bbox_id": "1583398575542-4-5",
					"contents": [
						212,
						86,
						33,
						28
					]
				},
				{
					"bbox_id": "1583398575542-4-6",
					"contents": [
						242,
						86,
						26,
						28
					]
				},
				{
					"bbox_id": "1583398575542-4-8",
					"contents": [
						288,
						86,
						20,
						28
					]
				},
				{
					"bbox_id": "1583398575542-4-9",
					"contents": [
						311,
						86,
						26,
						28
					]
				},
				{
					"bbox_id": "1583398575542-4-10",
					"contents": [
						336,
						86,
						25,
						28
					]
				},
				{
					"bbox_id": "1583398575542-4-11",
					"contents": [
						364,
						86,
						30,
						28
					]
				},
				{
					"bbox_id": "1583398575542-4-12",
					"contents": [
						397,
						86,
						36,
						28
					]
				},
				{
					"bbox_id": "1583398575542-4-14",
					"contents": [
						464,
						86,
						32,
						28
					]
				},
				{
					"bbox_id": "1583398575542-5-0",
					"contents": [
						54,
						107,
						27,
						21
					]
				},
				{
					"bbox_id": "1583398575542-5-1",
					"contents": [
						80,
						107,
						25,
						21
					]
				},
				{
					"bbox_id": "1583398575542-5-2",
					"contents": [
						102,
						107,
						19,
						21
					]
				},
				{
					"bbox_id": "1583398575542-5-3",
					"contents": [
						125,
						107,
						27,
						21
					]
				},
				{
					"bbox_id": "1583398575542-5-4",
					"contents": [
						147,
						107,
						17,
						21
					]
				},
				{
					"bbox_id": "1583398575542-5-7",
					"contents": [
						207,
						107,
						17,
						21
					]
				},
				{
					"bbox_id": "1583398575542-5-8",
					"contents": [
						225,
						107,
						19,
						21
					]
				},
				{
					"bbox_id": "1583398575542-5-10",
					"contents": [
						265,
						107,
						27,
						21
					]
				},
				{
					"bbox_id": "1583398575542-6-1",
					"contents": [
						199,
						124,
						23,
						28
					]
				},
				{
					"bbox_id": "1583398575542-6-2",
					"contents": [
						222,
						124,
						23,
						28
					]
				},
				{
					"bbox_id": "1583398575542-6-3",
					"contents": [
						252,
						124,
						36,
						28
					]
				},
				{
					"bbox_id": "1583398575542-6-4",
					"contents": [
						285,
						124,
						30,
						28
					]
				},
				{
					"bbox_id": "1583398575542-6-5",
					"contents": [
						315,
						124,
						30,
						28
					]
				},
				{
					"bbox_id": "1583398575542-6-6",
					"contents": [
						345,
						124,
						30,
						28
					]
				},
				{
					"bbox_id": "1583398575542-6-8",
					"contents": [
						396,
						124,
						20,
						28
					]
				},
				{
					"bbox_id": "1583398575542-6-9",
					"contents": [
						419,
						124,
						26,
						28
					]
				},
				{
					"bbox_id": "1583398575542-6-11",
					"contents": [
						473,
						124,
						30,
						28
					]
				},
				{
					"bbox_id": "1583398575542-7-0",
					"contents": [
						106,
						143,
						27,
						26
					]
				},
				{
					"bbox_id": "1583398575542-7-1",
					"contents": [
						135,
						143,
						30,
						26
					]
				},
				{
					"bbox_id": "1583398575542-7-2",
					"contents": [
						163,
						143,
						27,
						26
					]
				},
				{
					"bbox_id": "1583398575542-7-3",
					"contents": [
						187,
						143,
						20,
						26
					]
				},
				{
					"bbox_id": "1583398575542-7-5",
					"contents": [
						242,
						143,
						36,
						26
					]
				},
				{
					"bbox_id": "1583398575542-7-9",
					"contents": [
						363,
						143,
						27,
						26
					]
				},
				{
					"bbox_id": "1583398575542-7-11",
					"contents": [
						422,
						143,
						36,
						26
					]
				},
				{
					"bbox_id": "1583398575542-7-12",
					"contents": [
						452,
						143,
						24,
						26
					]
				},
				{
					"bbox_id": "1583398575542-7-13",
					"contents": [
						476,
						143,
						24,
						26
					]
				},
				{
					"bbox_id": "1583398575542-8-4",
					"contents": [
						156,
						157,
						17,
						19
					]
				},
				{
					"bbox_id": "1583398575542-8-5",
					"contents": [
						175,
						157,
						21,
						19
					]
				},
				{
					"bbox_id": "1583398575542-8-6",
					"contents": [
						192,
						157,
						12,
						19
					]
				},
				{
					"bbox_id": "1583398575542-8-7",
					"contents": [
						206,
						157,
						16,
						19
					]
				},
				{
					"bbox_id": "1583398575542-8-8",
					"contents": [
						221,
						157,
						14,
						19
					]
				},
				{
					"bbox_id": "1583398575542-8-9",
					"contents": [
						236,
						157,
						16,
						19
					]
				},
				{
					"bbox_id": "1583398575542-8-12",
					"contents": [
						290,
						157,
						20,
						19
					]
				},
				{
					"bbox_id": "1583398575542-8-13",
					"contents": [
						310,
						157,
						20,
						19
					]
				},
				{
					"bbox_id": "1583398575542-8-14",
					"contents": [
						327,
						157,
						15,
						19
					]
				},
				{
					"bbox_id": "1583398575542-8-15",
					"contents": [
						345,
						157,
						21,
						19
					]
				},
				{
					"bbox_id": "1583398575542-8-19",
					"contents": [
						415,
						157,
						17,
						19
					]
				},
				{
					"bbox_id": "1583398575542-8-22",
					"contents": [
						473,
						157,
						22,
						19
					]
				},
				{
					"bbox_id": "1583398575542-8-23",
					"contents": [
						494,
						157,
						20,
						19
					]
				},
				{
					"bbox_id": "1583398575542-9-0",
					"contents": [
						31,
						175,
						17,
						20
					]
				},
				{
					"bbox_id": "1583398575542-9-1",
					"contents": [
						50,
						175,
						20,
						20
					]
				},
				{
					"bbox_id": "1583398575542-9-3",
					"contents": [
						87,
						175,
						20,
						20
					]
				},
				{
					"bbox_id": "1583398575542-9-4",
					"contents": [
						107,
						175,
						20,
						20
					]
				},
				{
					"bbox_id": "1583398575542-9-6",
					"contents": [
						142,
						175,
						16,
						20
					]
				},
				{
					"bbox_id": "1583398575542-9-7",
					"contents": [
						162,
						175,
						25,
						20
					]
				},
				{
					"bbox_id": "1583398575542-9-8",
					"contents": [
						184,
						175,
						19,
						20
					]
				},
				{
					"bbox_id": "1583398575542-9-10",
					"contents": [
						222,
						175,
						19,
						20
					]
				},
				{
					"bbox_id": "1583398575542-9-11",
					"contents": [
						242,
						175,
						21,
						20
					]
				},
				{
					"bbox_id": "1583398575542-9-12",
					"contents": [
						260,
						175,
						14,
						20
					]
				},
				{
					"bbox_id": "1583398575542-9-14",
					"contents": [
						289,
						175,
						14,
						20
					]
				},
				{
					"bbox_id": "1583398575542-9-15",
					"contents": [
						304,
						175,
						16,
						20
					]
				},
				{
					"bbox_id": "1583398575542-9-17",
					"contents": [
						343,
						175,
						22,
						20
					]
				},
				{
					"bbox_id": "1583398575542-9-18",
					"contents": [
						362,
						175,
						17,
						20
					]
				},
				{
					"bbox_id": "1583398575542-9-20",
					"contents": [
						401,
						175,
						17,
						20
					]
				},
				{
					"bbox_id": "1583398575542-9-21",
					"contents": [
						420,
						175,
						20,
						20
					]
				},
				{
					"bbox_id": "1583398575542-9-22",
					"contents": [
						440,
						175,
						20,
						20
					]
				},
				{
					"bbox_id": "1583398575542-9-23",
					"contents": [
						460,
						175,
						21,
						20
					]
				},
				{
					"bbox_id": "1583398575542-9-24",
					"contents": [
						480,
						175,
						19,
						20
					]
				},
				{
					"bbox_id": "1583398575542-9-25",
					"contents": [
						501,
						175,
						22,
						20
					]
				},
				{
					"bbox_id": "1583398575542-10-0",
					"contents": [
						152,
						194,
						17,
						21
					]
				},
				{
					"bbox_id": "1583398575542-10-1",
					"contents": [
						171,
						194,
						20,
						21
					]
				},
				{
					"bbox_id": "1583398575542-10-2",
					"contents": [
						189,
						194,
						17,
						21
					]
				},
				{
					"bbox_id": "1583398575542-10-3",
					"contents": [
						211,
						194,
						27,
						21
					]
				},
				{
					"bbox_id": "1583398575542-10-4",
					"contents": [
						233,
						194,
						16,
						21
					]
				},
				{
					"bbox_id": "1583398575542-10-5",
					"contents": [
						254,
						194,
						27,
						21
					]
				},
				{
					"bbox_id": "1583398575542-10-6",
					"contents": [
						278,
						194,
						21,
						21
					]
				},
				{
					"bbox_id": "1583398575542-10-7",
					"contents": [
						298,
						194,
						18,
						21
					]
				},
				{
					"bbox_id": "1583398575542-10-8",
					"contents": [
						315,
						194,
						16,
						21
					]
				},
				{
					"bbox_id": "1583398575542-10-9",
					"contents": [
						332,
						194,
						18,
						21
					]
				},
				{
					"bbox_id": "1583398575542-10-10",
					"contents": [
						349,
						194,
						17,
						21
					]
				},
				{
					"bbox_id": "1583398575542-10-12",
					"contents": [
						383,
						194,
						20,
						21
					]
				},
				{
					"bbox_id": "1583398575542-10-18",
					"contents": [
						483,
						194,
						16,
						21
					]
				},
				{
					"bbox_id": "1583398575542-11-0",
					"contents": [
						109,
						211,
						36,
						27
					]
				},
				{
					"bbox_id": "1583398575542-11-1",
					"contents": [
						139,
						211,
						25,
						27
					]
				},
				{
					"bbox_id": "1583398575542-11-2",
					"contents": [
						170,
						211,
						36,
						27
					]
				},
				{
					"bbox_id": "1583398575542-11-3",
					"contents": [
						200,
						211,
						25,
						27
					]
				},
				{
					"bbox_id": "1583398575542-11-4",
					"contents": [
						229,
						211,
						33,
						27
					]
				},
				{
					"bbox_id": "1583398575542-11-6",
					"contents": [
						284,
						211,
						27,
						27
					]
				},
				{
					"bbox_id": "1583398575542-12-1",
					"contents": [
						159,
						233,
						25,
						24
					]
				},
				{
					"bbox_id": "1583398575542-12-2",
					"contents": [
						185,
						233,
						27,
						24
					]
				},
				{
					"bbox_id": "1583398575542-12-3",
					"contents": [
						212,
						233,
						27,
						24
					]
				},
				{
					"bbox_id": "1583398575542-12-4",
					"contents": [
						238,
						233,
						25,
						24
					]
				},
				{
					"bbox_id": "1583398575542-12-5",
					"contents": [
						260,
						233,
						18,
						24
					]
				},
				{
					"bbox_id": "1583398575542-12-6",
					"contents": [
						282,
						233,
						27,
						24
					]
				},
				{
					"bbox_id": "1583398575542-12-8",
					"contents": [
						326,
						233,
						11,
						24
					]
				},
				{
					"bbox_id": "1583398575542-12-9",
					"contents": [
						345,
						233,
						27,
						24
					]
				},
				{
					"bbox_id": "1583398575542-12-10",
					"contents": [
						371,
						233,
						25,
						24
					]
				},
				{
					"bbox_id": "1583398575542-12-11",
					"contents": [
						395,
						233,
						23,
						24
					]
				},
				{
					"bbox_id": "1583398575542-12-13",
					"contents": [
						446,
						233,
						30,
						24
					]
				},
				{
					"bbox_id": "1583398575542-12-14",
					"contents": [
						468,
						233,
						15,
						24
					]
				},
				{
					"bbox_id": "1583398575542-12-15",
					"contents": [
						489,
						233,
						27,
						24
					]
				},
				{
					"bbox_id": "1583398575542-13-0",
					"contents": [
						69,
						246,
						30,
						22
					]
				},
				{
					"bbox_id": "1583398575542-13-3",
					"contents": [
						146,
						246,
						20,
						22
					]
				},
				{
					"bbox_id": "1583398575542-13-5",
					"contents": [
						201,
						246,
						30,
						22
					]
				},
				{
					"bbox_id": "1583398575542-13-7",
					"contents": [
						253,
						246,
						20,
						22
					]
				},
				{
					"bbox_id": "1583398575542-13-8",
					"contents": [
						274,
						246,
						23,
						22
					]
				},
				{
					"bbox_id": "1583398575542-13-11",
					"contents": [
						342,
						246,
						21,
						22
					]
				},
				{
					"bbox_id": "1583398575542-13-12",
					"contents": [
						363,
						246,
						21,
						22
					]
				},
				{
					"bbox_id": "1583398575542-13-14",
					"contents": [
						403,
						246,
						20,
						22
					]
				},
				{
					"bbox_id": "1583398575542-13-16",
					"contents": [
						451,
						246,
						27,
						22
					]
				}
			]
		}
	]
}