{
	"info": {},
	"license": {},
	"images": [
		{
			"id": "1583398671155",
			"width": 512,
			"height": 512,
			"file_name": "1583398671155-724.jpg",
			"data_captured": 1583398671.991015
		}
	],
	"annotations": [
		{
			"id": "1583398671155",
			"text": [
				{
					"text_id": "1583398671155-0-1",
					"contents": "y"
				},
				{
					"text_id": "1583398671155-0-4",
					"contents": "롯"
				},
				{
					"text_id": "1583398671155-0-5",
					"contents": "늠"
				},
				{
					"text_id": "1583398671155-0-6",
					"contents": "쉰"
				},
				{
					"text_id": "1583398671155-0-7",
					"contents": "조"
				},
				{
					"text_id": "1583398671155-0-8",
					"contents": "녁"
				},
				{
					"text_id": "1583398671155-0-9",
					"contents": "펜"
				},
				{
					"text_id": "1583398671155-0-10",
					"contents": "건"
				},
				{
					"text_id": "1583398671155-0-12",
					"contents": "샤"
				},
				{
					"text_id": "1583398671155-1-0",
					"contents": "콘"
				},
				{
					"text_id": "1583398671155-1-1",
					"contents": "카"
				},
				{
					"text_id": "1583398671155-1-2",
					"contents": "콧"
				},
				{
					"text_id": "1583398671155-1-3",
					"contents": "cc"
				},
				{
					"text_id": "1583398671155-1-4",
					"contents": "캘"
				},
				{
					"text_id": "1583398671155-1-5",
					"contents": "발"
				},
				{
					"text_id": "1583398671155-1-6",
					"contents": "룡"
				},
				{
					"text_id": "1583398671155-1-7",
					"contents": "쪼"
				},
				{
					"text_id": "1583398671155-1-8",
					"contents": "갈"
				},
				{
					"text_id": "1583398671155-1-9",
					"contents": "콜"
				},
				{
					"text_id": "1583398671155-2-0",
					"contents": "쳔"
				},
				{
					"text_id": "1583398671155-2-1",
					"contents": "윈"
				},
				{
					"text_id": "1583398671155-2-4",
					"contents": "샤"
				},
				{
					"text_id": "1583398671155-2-5",
					"contents": "강"
				},
				{
					"text_id": "1583398671155-2-6",
					"contents": "빚"
				},
				{
					"text_id": "1583398671155-2-8",
					"contents": "씽"
				},
				{
					"text_id": "1583398671155-2-9",
					"contents": "포"
				},
				{
					"text_id": "1583398671155-2-10",
					"contents": "찌"
				},
				{
					"text_id": "1583398671155-3-0",
					"contents": "품"
				},
				{
					"text_id": "1583398671155-3-1",
					"contents": "뚤"
				},
				{
					"text_id": "1583398671155-3-2",
					"contents": "훠"
				},
				{
					"text_id": "1583398671155-3-5",
					"contents": "세"
				},
				{
					"text_id": "1583398671155-3-11",
					"contents": "좁"
				},
				{
					"text_id": "1583398671155-3-12",
					"contents": "귀"
				},
				{
					"text_id": "1583398671155-3-13",
					"contents": "핸"
				},
				{
					"text_id": "1583398671155-4-0",
					"contents": "렙"
				},
				{
					"text_id": "1583398671155-4-1",
					"contents": "눌"
				},
				{
					"text_id": "1583398671155-4-2",
					"contents": "징"
				},
				{
					"text_id": "1583398671155-4-3",
					"contents": "cq"
				},
				{
					"text_id": "1583398671155-4-4",
					"contents": "덜"
				},
				{
					"text_id": "1583398671155-4-5",
					"contents": "렉"
				},
				{
					"text_id": "1583398671155-4-6",
					"contents": "롸"
				},
				{
					"text_id": "1583398671155-4-7",
					"contents": "레"
				},
				{
					"text_id": "1583398671155-4-8",
					"contents": "길"
				},
				{
					"text_id": "1583398671155-4-9",
					"contents": "ct"
				},
				{
					"text_id": "1583398671155-5-0",
					"contents": "응"
				},
				{
					"text_id": "1583398671155-5-1",
					"contents": "6"
				},
				{
					"text_id": "1583398671155-5-2",
					"contents": "택"
				},
				{
					"text_id": "1583398671155-5-3",
					"contents": "해"
				},
				{
					"text_id": "1583398671155-5-4",
					"contents": "국"
				},
				{
					"text_id": "1583398671155-5-5",
					"contents": "삽"
				},
				{
					"text_id": "1583398671155-5-6",
					"contents": "갱"
				},
				{
					"text_id": "1583398671155-5-7",
					"contents": "몬"
				},
				{
					"text_id": "1583398671155-5-9",
					"contents": "튠"
				},
				{
					"text_id": "1583398671155-6-1",
					"contents": "천"
				},
				{
					"text_id": "1583398671155-6-2",
					"contents": "합"
				},
				{
					"text_id": "1583398671155-6-4",
					"contents": "꼬"
				},
				{
					"text_id": "1583398671155-6-5",
					"contents": "딥"
				},
				{
					"text_id": "1583398671155-6-6",
					"contents": "질"
				},
				{
					"text_id": "1583398671155-6-7",
					"contents": "참"
				},
				{
					"text_id": "1583398671155-6-8",
					"contents": "c"
				},
				{
					"text_id": "1583398671155-6-11",
					"contents": "렴"
				},
				{
					"text_id": "1583398671155-6-13",
					"contents": "빛"
				},
				{
					"text_id": "1583398671155-6-14",
					"contents": "퀼"
				},
				{
					"text_id": "1583398671155-7-1",
					"contents": "뫼"
				},
				{
					"text_id": "1583398671155-7-3",
					"contents": "p"
				},
				{
					"text_id": "1583398671155-7-4",
					"contents": "틱"
				},
				{
					"text_id": "1583398671155-7-6",
					"contents": "직"
				},
				{
					"text_id": "1583398671155-7-7",
					"contents": "들"
				},
				{
					"text_id": "1583398671155-7-8",
					"contents": "험"
				},
				{
					"text_id": "1583398671155-7-10",
					"contents": "즌"
				},
				{
					"text_id": "1583398671155-7-11",
					"contents": "껀"
				},
				{
					"text_id": "1583398671155-7-13",
					"contents": "허"
				},
				{
					"text_id": "1583398671155-7-14",
					"contents": "푹"
				},
				{
					"text_id": "1583398671155-7-15",
					"contents": "꼴"
				},
				{
					"text_id": "1583398671155-7-16",
					"contents": "율"
				},
				{
					"text_id": "1583398671155-7-17",
					"contents": "팀"
				},
				{
					"text_id": "1583398671155-7-18",
					"contents": "젯"
				},
				{
					"text_id": "1583398671155-8-0",
					"contents": "탁"
				},
				{
					"text_id": "1583398671155-8-1",
					"contents": "듀"
				},
				{
					"text_id": "1583398671155-8-2",
					"contents": "투"
				},
				{
					"text_id": "1583398671155-8-6",
					"contents": "클"
				},
				{
					"text_id": "1583398671155-8-7",
					"contents": "탕"
				},
				{
					"text_id": "1583398671155-8-8",
					"contents": "서"
				},
				{
					"text_id": "1583398671155-8-10",
					"contents": "둘"
				},
				{
					"text_id": "1583398671155-8-11",
					"contents": "나"
				},
				{
					"text_id": "1583398671155-9-1",
					"contents": "욤"
				},
				{
					"text_id": "1583398671155-9-3",
					"contents": "백"
				},
				{
					"text_id": "1583398671155-9-4",
					"contents": "젬"
				},
				{
					"text_id": "1583398671155-9-5",
					"contents": "챨"
				},
				{
					"text_id": "1583398671155-9-6",
					"contents": "멧"
				},
				{
					"text_id": "1583398671155-9-7",
					"contents": "싼"
				},
				{
					"text_id": "1583398671155-9-8",
					"contents": "땡"
				},
				{
					"text_id": "1583398671155-9-9",
					"contents": "갸"
				},
				{
					"text_id": "1583398671155-9-10",
					"contents": "붓"
				},
				{
					"text_id": "1583398671155-9-11",
					"contents": "욘"
				},
				{
					"text_id": "1583398671155-9-12",
					"contents": "런"
				},
				{
					"text_id": "1583398671155-9-13",
					"contents": "얄"
				},
				{
					"text_id": "1583398671155-9-15",
					"contents": "펜"
				},
				{
					"text_id": "1583398671155-9-16",
					"contents": "뽀"
				},
				{
					"text_id": "1583398671155-9-17",
					"contents": "바"
				},
				{
					"text_id": "1583398671155-10-1",
					"contents": "낌"
				},
				{
					"text_id": "1583398671155-10-2",
					"contents": "캉"
				},
				{
					"text_id": "1583398671155-10-3",
					"contents": "들"
				},
				{
					"text_id": "1583398671155-10-4",
					"contents": "은"
				},
				{
					"text_id": "1583398671155-10-5",
					"contents": "괴"
				},
				{
					"text_id": "1583398671155-10-7",
					"contents": "셈"
				},
				{
					"text_id": "1583398671155-10-8",
					"contents": "핌"
				},
				{
					"text_id": "1583398671155-10-9",
					"contents": "띵"
				},
				{
					"text_id": "1583398671155-10-10",
					"contents": "1"
				},
				{
					"text_id": "1583398671155-10-13",
					"contents": "놀"
				},
				{
					"text_id": "1583398671155-11-0",
					"contents": "붙"
				},
				{
					"text_id": "1583398671155-11-1",
					"contents": "돌"
				},
				{
					"text_id": "1583398671155-11-2",
					"contents": "호"
				},
				{
					"text_id": "1583398671155-11-3",
					"contents": "웽"
				},
				{
					"text_id": "1583398671155-11-6",
					"contents": "지"
				},
				{
					"text_id": "1583398671155-11-7",
					"contents": "르"
				},
				{
					"text_id": "1583398671155-11-8",
					"contents": "손"
				},
				{
					"text_id": "1583398671155-11-9",
					"contents": "익"
				}
			],
			"bbox": [
				{
					"bbox_id": "1583398671155-0-1",
					"contents": [
						101,
						18,
						60,
						32
					]
				},
				{
					"bbox_id": "1583398671155-0-4",
					"contents": [
						219,
						18,
						36,
						32
					]
				},
				{
					"bbox_id": "1583398671155-0-5",
					"contents": [
						254,
						18,
						34,
						32
					]
				},
				{
					"bbox_id": "1583398671155-0-6",
					"contents": [
						289,
						18,
						36,
						32
					]
				},
				{
					"bbox_id": "1583398671155-0-7",
					"contents": [
						322,
						18,
						31,
						32
					]
				},
				{
					"bbox_id": "1583398671155-0-8",
					"contents": [
						355,
						18,
						34,
						32
					]
				},
				{
					"bbox_id": "1583398671155-0-9",
					"contents": [
						388,
						18,
						33,
						32
					]
				},
				{
					"bbox_id": "1583398671155-0-10",
					"contents": [
						418,
						18,
						26,
						32
					]
				},
				{
					"bbox_id": "1583398671155-0-12",
					"contents": [
						476,
						18,
						36,
						32
					]
				},
				{
					"bbox_id": "1583398671155-1-0",
					"contents": [
						170,
						40,
						26,
						32
					]
				},
				{
					"bbox_id": "1583398671155-1-1",
					"contents": [
						200,
						40,
						34,
						32
					]
				},
				{
					"bbox_id": "1583398671155-1-2",
					"contents": [
						232,
						40,
						30,
						32
					]
				},
				{
					"bbox_id": "1583398671155-1-3",
					"contents": [
						277,
						40,
						60,
						32
					]
				},
				{
					"bbox_id": "1583398671155-1-4",
					"contents": [
						323,
						40,
						33,
						32
					]
				},
				{
					"bbox_id": "1583398671155-1-5",
					"contents": [
						358,
						40,
						36,
						32
					]
				},
				{
					"bbox_id": "1583398671155-1-6",
					"contents": [
						393,
						40,
						35,
						32
					]
				},
				{
					"bbox_id": "1583398671155-1-7",
					"contents": [
						429,
						40,
						36,
						32
					]
				},
				{
					"bbox_id": "1583398671155-1-8",
					"contents": [
						463,
						40,
						33,
						32
					]
				},
				{
					"bbox_id": "1583398671155-1-9",
					"contents": [
						492,
						40,
						25,
						32
					]
				},
				{
					"bbox_id": "1583398671155-2-0",
					"contents": [
						147,
						61,
						25,
						23
					]
				},
				{
					"bbox_id": "1583398671155-2-1",
					"contents": [
						170,
						61,
						20,
						23
					]
				},
				{
					"bbox_id": "1583398671155-2-4",
					"contents": [
						246,
						61,
						25,
						23
					]
				},
				{
					"bbox_id": "1583398671155-2-5",
					"contents": [
						272,
						61,
						26,
						23
					]
				},
				{
					"bbox_id": "1583398671155-2-6",
					"contents": [
						296,
						61,
						22,
						23
					]
				},
				{
					"bbox_id": "1583398671155-2-8",
					"contents": [
						344,
						61,
						20,
						23
					]
				},
				{
					"bbox_id": "1583398671155-2-9",
					"contents": [
						370,
						61,
						33,
						23
					]
				},
				{
					"bbox_id": "1583398671155-2-10",
					"contents": [
						399,
						61,
						25,
						23
					]
				},
				{
					"bbox_id": "1583398671155-3-0",
					"contents": [
						166,
						76,
						27,
						23
					]
				},
				{
					"bbox_id": "1583398671155-3-1",
					"contents": [
						189,
						76,
						18,
						23
					]
				},
				{
					"bbox_id": "1583398671155-3-2",
					"contents": [
						211,
						76,
						26,
						23
					]
				},
				{
					"bbox_id": "1583398671155-3-5",
					"contents": [
						282,
						76,
						20,
						23
					]
				},
				{
					"bbox_id": "1583398671155-3-11",
					"contents": [
						423,
						76,
						27,
						23
					]
				},
				{
					"bbox_id": "1583398671155-3-12",
					"contents": [
						449,
						76,
						24,
						23
					]
				},
				{
					"bbox_id": "1583398671155-3-13",
					"contents": [
						473,
						76,
						25,
						23
					]
				},
				{
					"bbox_id": "1583398671155-4-0",
					"contents": [
						107,
						104,
						33,
						33
					]
				},
				{
					"bbox_id": "1583398671155-4-1",
					"contents": [
						142,
						104,
						36,
						33
					]
				},
				{
					"bbox_id": "1583398671155-4-2",
					"contents": [
						176,
						104,
						33,
						33
					]
				},
				{
					"bbox_id": "1583398671155-4-3",
					"contents": [
						223,
						104,
						60,
						33
					]
				},
				{
					"bbox_id": "1583398671155-4-4",
					"contents": [
						269,
						104,
						32,
						33
					]
				},
				{
					"bbox_id": "1583398671155-4-5",
					"contents": [
						298,
						104,
						26,
						33
					]
				},
				{
					"bbox_id": "1583398671155-4-6",
					"contents": [
						328,
						104,
						35,
						33
					]
				},
				{
					"bbox_id": "1583398671155-4-7",
					"contents": [
						362,
						104,
						33,
						33
					]
				},
				{
					"bbox_id": "1583398671155-4-8",
					"contents": [
						397,
						104,
						36,
						33
					]
				},
				{
					"bbox_id": "1583398671155-4-9",
					"contents": [
						445,
						104,
						60,
						33
					]
				},
				{
					"bbox_id": "1583398671155-5-0",
					"contents": [
						99,
						121,
						32,
						32
					]
				},
				{
					"bbox_id": "1583398671155-5-1",
					"contents": [
						145,
						121,
						60,
						32
					]
				},
				{
					"bbox_id": "1583398671155-5-2",
					"contents": [
						193,
						121,
						36,
						32
					]
				},
				{
					"bbox_id": "1583398671155-5-3",
					"contents": [
						227,
						121,
						33,
						32
					]
				},
				{
					"bbox_id": "1583398671155-5-4",
					"contents": [
						260,
						121,
						33,
						32
					]
				},
				{
					"bbox_id": "1583398671155-5-5",
					"contents": [
						295,
						121,
						36,
						32
					]
				},
				{
					"bbox_id": "1583398671155-5-6",
					"contents": [
						331,
						121,
						36,
						32
					]
				},
				{
					"bbox_id": "1583398671155-5-7",
					"contents": [
						365,
						121,
						33,
						32
					]
				},
				{
					"bbox_id": "1583398671155-5-9",
					"contents": [
						460,
						121,
						36,
						32
					]
				},
				{
					"bbox_id": "1583398671155-6-1",
					"contents": [
						180,
						138,
						20,
						23
					]
				},
				{
					"bbox_id": "1583398671155-6-2",
					"contents": [
						200,
						138,
						20,
						23
					]
				},
				{
					"bbox_id": "1583398671155-6-4",
					"contents": [
						246,
						138,
						19,
						23
					]
				},
				{
					"bbox_id": "1583398671155-6-5",
					"contents": [
						269,
						138,
						27,
						23
					]
				},
				{
					"bbox_id": "1583398671155-6-6",
					"contents": [
						295,
						138,
						25,
						23
					]
				},
				{
					"bbox_id": "1583398671155-6-7",
					"contents": [
						318,
						138,
						20,
						23
					]
				},
				{
					"bbox_id": "1583398671155-6-8",
					"contents": [
						343,
						138,
						30,
						23
					]
				},
				{
					"bbox_id": "1583398671155-6-11",
					"contents": [
						427,
						138,
						25,
						23
					]
				},
				{
					"bbox_id": "1583398671155-6-13",
					"contents": [
						473,
						138,
						27,
						23
					]
				},
				{
					"bbox_id": "1583398671155-6-14",
					"contents": [
						497,
						138,
						20,
						23
					]
				},
				{
					"bbox_id": "1583398671155-7-1",
					"contents": [
						94,
						167,
						19,
						23
					]
				},
				{
					"bbox_id": "1583398671155-7-3",
					"contents": [
						138,
						167,
						30,
						23
					]
				},
				{
					"bbox_id": "1583398671155-7-4",
					"contents": [
						161,
						167,
						17,
						23
					]
				},
				{
					"bbox_id": "1583398671155-7-6",
					"contents": [
						207,
						167,
						25,
						23
					]
				},
				{
					"bbox_id": "1583398671155-7-7",
					"contents": [
						233,
						167,
						27,
						23
					]
				},
				{
					"bbox_id": "1583398671155-7-8",
					"contents": [
						257,
						167,
						20,
						23
					]
				},
				{
					"bbox_id": "1583398671155-7-10",
					"contents": [
						301,
						167,
						20,
						23
					]
				},
				{
					"bbox_id": "1583398671155-7-11",
					"contents": [
						324,
						167,
						27,
						23
					]
				},
				{
					"bbox_id": "1583398671155-7-13",
					"contents": [
						377,
						167,
						24,
						23
					]
				},
				{
					"bbox_id": "1583398671155-7-14",
					"contents": [
						398,
						167,
						19,
						23
					]
				},
				{
					"bbox_id": "1583398671155-7-15",
					"contents": [
						420,
						167,
						25,
						23
					]
				},
				{
					"bbox_id": "1583398671155-7-16",
					"contents": [
						445,
						167,
						25,
						23
					]
				},
				{
					"bbox_id": "1583398671155-7-17",
					"contents": [
						468,
						167,
						20,
						23
					]
				},
				{
					"bbox_id": "1583398671155-7-18",
					"contents": [
						491,
						167,
						27,
						23
					]
				},
				{
					"bbox_id": "1583398671155-8-0",
					"contents": [
						160,
						183,
						35,
						29
					]
				},
				{
					"bbox_id": "1583398671155-8-1",
					"contents": [
						187,
						183,
						19,
						29
					]
				},
				{
					"bbox_id": "1583398671155-8-2",
					"contents": [
						209,
						183,
						24,
						29
					]
				},
				{
					"bbox_id": "1583398671155-8-6",
					"contents": [
						323,
						183,
						26,
						29
					]
				},
				{
					"bbox_id": "1583398671155-8-7",
					"contents": [
						348,
						183,
						25,
						29
					]
				},
				{
					"bbox_id": "1583398671155-8-8",
					"contents": [
						379,
						183,
						36,
						29
					]
				},
				{
					"bbox_id": "1583398671155-8-10",
					"contents": [
						450,
						183,
						36,
						29
					]
				},
				{
					"bbox_id": "1583398671155-8-11",
					"contents": [
						484,
						183,
						33,
						29
					]
				},
				{
					"bbox_id": "1583398671155-9-1",
					"contents": [
						109,
						206,
						27,
						23
					]
				},
				{
					"bbox_id": "1583398671155-9-3",
					"contents": [
						163,
						206,
						27,
						23
					]
				},
				{
					"bbox_id": "1583398671155-9-4",
					"contents": [
						190,
						206,
						27,
						23
					]
				},
				{
					"bbox_id": "1583398671155-9-5",
					"contents": [
						212,
						206,
						16,
						23
					]
				},
				{
					"bbox_id": "1583398671155-9-6",
					"contents": [
						232,
						206,
						25,
						23
					]
				},
				{
					"bbox_id": "1583398671155-9-7",
					"contents": [
						254,
						206,
						19,
						23
					]
				},
				{
					"bbox_id": "1583398671155-9-8",
					"contents": [
						274,
						206,
						20,
						23
					]
				},
				{
					"bbox_id": "1583398671155-9-9",
					"contents": [
						295,
						206,
						23,
						23
					]
				},
				{
					"bbox_id": "1583398671155-9-10",
					"contents": [
						317,
						206,
						20,
						23
					]
				},
				{
					"bbox_id": "1583398671155-9-11",
					"contents": [
						340,
						206,
						27,
						23
					]
				},
				{
					"bbox_id": "1583398671155-9-12",
					"contents": [
						364,
						206,
						20,
						23
					]
				},
				{
					"bbox_id": "1583398671155-9-13",
					"contents": [
						387,
						206,
						27,
						23
					]
				},
				{
					"bbox_id": "1583398671155-9-15",
					"contents": [
						432,
						206,
						25,
						23
					]
				},
				{
					"bbox_id": "1583398671155-9-16",
					"contents": [
						455,
						206,
						21,
						23
					]
				},
				{
					"bbox_id": "1583398671155-9-17",
					"contents": [
						479,
						206,
						27,
						23
					]
				},
				{
					"bbox_id": "1583398671155-10-1",
					"contents": [
						84,
						225,
						36,
						29
					]
				},
				{
					"bbox_id": "1583398671155-10-2",
					"contents": [
						118,
						225,
						33,
						29
					]
				},
				{
					"bbox_id": "1583398671155-10-3",
					"contents": [
						151,
						225,
						33,
						29
					]
				},
				{
					"bbox_id": "1583398671155-10-4",
					"contents": [
						181,
						225,
						26,
						29
					]
				},
				{
					"bbox_id": "1583398671155-10-5",
					"contents": [
						211,
						225,
						35,
						29
					]
				},
				{
					"bbox_id": "1583398671155-10-7",
					"contents": [
						283,
						225,
						36,
						29
					]
				},
				{
					"bbox_id": "1583398671155-10-8",
					"contents": [
						319,
						225,
						36,
						29
					]
				},
				{
					"bbox_id": "1583398671155-10-9",
					"contents": [
						353,
						225,
						33,
						29
					]
				},
				{
					"bbox_id": "1583398671155-10-10",
					"contents": [
						385,
						225,
						30,
						29
					]
				},
				{
					"bbox_id": "1583398671155-10-13",
					"contents": [
						478,
						225,
						25,
						29
					]
				},
				{
					"bbox_id": "1583398671155-11-0",
					"contents": [
						142,
						249,
						25,
						32
					]
				},
				{
					"bbox_id": "1583398671155-11-1",
					"contents": [
						173,
						249,
						36,
						32
					]
				},
				{
					"bbox_id": "1583398671155-11-2",
					"contents": [
						209,
						249,
						36,
						32
					]
				},
				{
					"bbox_id": "1583398671155-11-3",
					"contents": [
						240,
						249,
						26,
						32
					]
				},
				{
					"bbox_id": "1583398671155-11-6",
					"contents": [
						362,
						249,
						32,
						32
					]
				},
				{
					"bbox_id": "1583398671155-11-7",
					"contents": [
						401,
						249,
						46,
						32
					]
				},
				{
					"bbox_id": "1583398671155-11-8",
					"contents": [
						441,
						249,
						35,
						32
					]
				},
				{
					"bbox_id": "1583398671155-11-9",
					"contents": [
						477,
						249,
						36,
						32
					]
				}
			]
		}
	]
}