{
	"info": {},
	"license": {},
	"images": [
		{
			"id": "1583398240023",
			"width": 512,
			"height": 512,
			"file_name": "1583398240023-186.jpg",
			"data_captured": 1583398240.674921
		}
	],
	"annotations": [
		{
			"id": "1583398240023",
			"text": [
				{
					"text_id": "1583398240023-0-0",
					"contents": "콰"
				},
				{
					"text_id": "1583398240023-0-1",
					"contents": "헴"
				},
				{
					"text_id": "1583398240023-0-2",
					"contents": "콥"
				},
				{
					"text_id": "1583398240023-0-3",
					"contents": "갠"
				},
				{
					"text_id": "1583398240023-0-4",
					"contents": "울"
				},
				{
					"text_id": "1583398240023-0-7",
					"contents": "뽀"
				},
				{
					"text_id": "1583398240023-0-8",
					"contents": "함"
				},
				{
					"text_id": "1583398240023-0-9",
					"contents": "ce"
				},
				{
					"text_id": "1583398240023-0-10",
					"contents": "갱"
				},
				{
					"text_id": "1583398240023-0-11",
					"contents": "산"
				},
				{
					"text_id": "1583398240023-0-12",
					"contents": "닷"
				},
				{
					"text_id": "1583398240023-0-13",
					"contents": "왼"
				},
				{
					"text_id": "1583398240023-0-14",
					"contents": "해"
				},
				{
					"text_id": "1583398240023-1-0",
					"contents": "휴"
				},
				{
					"text_id": "1583398240023-1-1",
					"contents": "퀼"
				},
				{
					"text_id": "1583398240023-1-2",
					"contents": "붐"
				},
				{
					"text_id": "1583398240023-1-4",
					"contents": "져"
				},
				{
					"text_id": "1583398240023-1-6",
					"contents": "블"
				},
				{
					"text_id": "1583398240023-1-9",
					"contents": "탄"
				},
				{
					"text_id": "1583398240023-1-10",
					"contents": "관"
				},
				{
					"text_id": "1583398240023-1-11",
					"contents": "오"
				},
				{
					"text_id": "1583398240023-2-0",
					"contents": "얄"
				},
				{
					"text_id": "1583398240023-2-1",
					"contents": "캐"
				},
				{
					"text_id": "1583398240023-2-2",
					"contents": "팡"
				},
				{
					"text_id": "1583398240023-2-3",
					"contents": "강"
				},
				{
					"text_id": "1583398240023-2-4",
					"contents": "칸"
				},
				{
					"text_id": "1583398240023-2-5",
					"contents": "방"
				},
				{
					"text_id": "1583398240023-2-6",
					"contents": "소"
				},
				{
					"text_id": "1583398240023-2-7",
					"contents": "께"
				},
				{
					"text_id": "1583398240023-2-8",
					"contents": "눅"
				},
				{
					"text_id": "1583398240023-2-10",
					"contents": "클"
				},
				{
					"text_id": "1583398240023-2-11",
					"contents": "작"
				},
				{
					"text_id": "1583398240023-3-1",
					"contents": "o"
				},
				{
					"text_id": "1583398240023-3-2",
					"contents": "양"
				},
				{
					"text_id": "1583398240023-3-3",
					"contents": "덱"
				},
				{
					"text_id": "1583398240023-3-4",
					"contents": "꿀"
				},
				{
					"text_id": "1583398240023-3-6",
					"contents": "던"
				},
				{
					"text_id": "1583398240023-3-7",
					"contents": "청"
				},
				{
					"text_id": "1583398240023-3-10",
					"contents": "특"
				},
				{
					"text_id": "1583398240023-3-11",
					"contents": "폰"
				},
				{
					"text_id": "1583398240023-3-12",
					"contents": "삿"
				},
				{
					"text_id": "1583398240023-3-13",
					"contents": "골"
				},
				{
					"text_id": "1583398240023-3-14",
					"contents": "랑"
				},
				{
					"text_id": "1583398240023-4-1",
					"contents": "쇄"
				},
				{
					"text_id": "1583398240023-4-2",
					"contents": "r"
				},
				{
					"text_id": "1583398240023-4-3",
					"contents": "붙"
				},
				{
					"text_id": "1583398240023-4-4",
					"contents": "야"
				},
				{
					"text_id": "1583398240023-4-6",
					"contents": "셉"
				},
				{
					"text_id": "1583398240023-4-8",
					"contents": "검"
				},
				{
					"text_id": "1583398240023-4-9",
					"contents": "판"
				},
				{
					"text_id": "1583398240023-4-10",
					"contents": "b"
				},
				{
					"text_id": "1583398240023-4-11",
					"contents": "제"
				},
				{
					"text_id": "1583398240023-4-12",
					"contents": "테"
				},
				{
					"text_id": "1583398240023-4-14",
					"contents": "ch"
				},
				{
					"text_id": "1583398240023-4-15",
					"contents": "궁"
				},
				{
					"text_id": "1583398240023-5-2",
					"contents": "목"
				},
				{
					"text_id": "1583398240023-5-3",
					"contents": "캘"
				},
				{
					"text_id": "1583398240023-5-4",
					"contents": "디"
				},
				{
					"text_id": "1583398240023-5-5",
					"contents": "앞"
				},
				{
					"text_id": "1583398240023-5-6",
					"contents": "cb"
				},
				{
					"text_id": "1583398240023-5-7",
					"contents": "댄"
				},
				{
					"text_id": "1583398240023-5-9",
					"contents": "쉬"
				},
				{
					"text_id": "1583398240023-5-10",
					"contents": "꼬"
				},
				{
					"text_id": "1583398240023-5-11",
					"contents": "방"
				},
				{
					"text_id": "1583398240023-5-13",
					"contents": "샨"
				},
				{
					"text_id": "1583398240023-5-14",
					"contents": "반"
				},
				{
					"text_id": "1583398240023-6-0",
					"contents": "럭"
				},
				{
					"text_id": "1583398240023-6-3",
					"contents": "꿈"
				},
				{
					"text_id": "1583398240023-6-4",
					"contents": "삿"
				},
				{
					"text_id": "1583398240023-6-6",
					"contents": "e"
				},
				{
					"text_id": "1583398240023-6-7",
					"contents": "동"
				},
				{
					"text_id": "1583398240023-6-8",
					"contents": "빛"
				},
				{
					"text_id": "1583398240023-6-10",
					"contents": "cs"
				},
				{
					"text_id": "1583398240023-7-0",
					"contents": "냇"
				},
				{
					"text_id": "1583398240023-7-1",
					"contents": "손"
				},
				{
					"text_id": "1583398240023-7-2",
					"contents": "용"
				},
				{
					"text_id": "1583398240023-7-3",
					"contents": "굴"
				},
				{
					"text_id": "1583398240023-7-5",
					"contents": "k"
				},
				{
					"text_id": "1583398240023-7-7",
					"contents": "걀"
				},
				{
					"text_id": "1583398240023-7-8",
					"contents": "쓰"
				},
				{
					"text_id": "1583398240023-7-9",
					"contents": "캔"
				},
				{
					"text_id": "1583398240023-7-10",
					"contents": "밸"
				},
				{
					"text_id": "1583398240023-7-11",
					"contents": "룸"
				},
				{
					"text_id": "1583398240023-7-13",
					"contents": "싸"
				},
				{
					"text_id": "1583398240023-7-14",
					"contents": "꿈"
				},
				{
					"text_id": "1583398240023-7-15",
					"contents": "더"
				},
				{
					"text_id": "1583398240023-8-1",
					"contents": "굼"
				},
				{
					"text_id": "1583398240023-8-3",
					"contents": "매"
				},
				{
					"text_id": "1583398240023-8-4",
					"contents": "5"
				},
				{
					"text_id": "1583398240023-8-5",
					"contents": "텐"
				},
				{
					"text_id": "1583398240023-8-6",
					"contents": "자"
				},
				{
					"text_id": "1583398240023-8-7",
					"contents": "cj"
				},
				{
					"text_id": "1583398240023-8-8",
					"contents": "시"
				},
				{
					"text_id": "1583398240023-8-11",
					"contents": "신"
				},
				{
					"text_id": "1583398240023-8-12",
					"contents": "앞"
				},
				{
					"text_id": "1583398240023-8-13",
					"contents": "룽"
				},
				{
					"text_id": "1583398240023-8-14",
					"contents": "쥐"
				},
				{
					"text_id": "1583398240023-8-15",
					"contents": "쿨"
				},
				{
					"text_id": "1583398240023-8-16",
					"contents": "엽"
				},
				{
					"text_id": "1583398240023-8-17",
					"contents": "막"
				},
				{
					"text_id": "1583398240023-8-18",
					"contents": "웨"
				},
				{
					"text_id": "1583398240023-9-2",
					"contents": "두"
				},
				{
					"text_id": "1583398240023-9-3",
					"contents": "방"
				},
				{
					"text_id": "1583398240023-9-6",
					"contents": "됴"
				},
				{
					"text_id": "1583398240023-9-7",
					"contents": "침"
				},
				{
					"text_id": "1583398240023-9-8",
					"contents": "움"
				},
				{
					"text_id": "1583398240023-9-9",
					"contents": "윌"
				},
				{
					"text_id": "1583398240023-9-10",
					"contents": "협"
				},
				{
					"text_id": "1583398240023-9-11",
					"contents": "롭"
				},
				{
					"text_id": "1583398240023-9-13",
					"contents": "연"
				},
				{
					"text_id": "1583398240023-9-14",
					"contents": "돈"
				},
				{
					"text_id": "1583398240023-9-16",
					"contents": "티"
				},
				{
					"text_id": "1583398240023-9-18",
					"contents": "묵"
				},
				{
					"text_id": "1583398240023-9-19",
					"contents": "랍"
				},
				{
					"text_id": "1583398240023-9-20",
					"contents": "임"
				},
				{
					"text_id": "1583398240023-10-0",
					"contents": "w"
				},
				{
					"text_id": "1583398240023-10-2",
					"contents": "갸"
				},
				{
					"text_id": "1583398240023-10-3",
					"contents": "퀼"
				},
				{
					"text_id": "1583398240023-10-4",
					"contents": "6"
				},
				{
					"text_id": "1583398240023-10-7",
					"contents": "택"
				},
				{
					"text_id": "1583398240023-10-8",
					"contents": "로"
				},
				{
					"text_id": "1583398240023-10-9",
					"contents": "시"
				},
				{
					"text_id": "1583398240023-10-10",
					"contents": "희"
				},
				{
					"text_id": "1583398240023-10-12",
					"contents": "킵"
				},
				{
					"text_id": "1583398240023-10-13",
					"contents": "곤"
				},
				{
					"text_id": "1583398240023-10-14",
					"contents": "텍"
				},
				{
					"text_id": "1583398240023-10-16",
					"contents": "율"
				},
				{
					"text_id": "1583398240023-10-17",
					"contents": "얍"
				},
				{
					"text_id": "1583398240023-11-1",
					"contents": "욜"
				},
				{
					"text_id": "1583398240023-11-2",
					"contents": "풀"
				},
				{
					"text_id": "1583398240023-11-3",
					"contents": "택"
				},
				{
					"text_id": "1583398240023-11-6",
					"contents": "변"
				},
				{
					"text_id": "1583398240023-11-7",
					"contents": "앵"
				},
				{
					"text_id": "1583398240023-11-9",
					"contents": "위"
				},
				{
					"text_id": "1583398240023-11-10",
					"contents": "룩"
				},
				{
					"text_id": "1583398240023-12-1",
					"contents": "시"
				},
				{
					"text_id": "1583398240023-12-2",
					"contents": "듦"
				},
				{
					"text_id": "1583398240023-12-7",
					"contents": "들"
				},
				{
					"text_id": "1583398240023-12-8",
					"contents": "익"
				},
				{
					"text_id": "1583398240023-12-9",
					"contents": "긍"
				},
				{
					"text_id": "1583398240023-12-12",
					"contents": "cy"
				},
				{
					"text_id": "1583398240023-12-13",
					"contents": "셉"
				}
			],
			"bbox": [
				{
					"bbox_id": "1583398240023-0-0",
					"contents": [
						42,
						19,
						32,
						29
					]
				},
				{
					"bbox_id": "1583398240023-0-1",
					"contents": [
						76,
						19,
						36,
						29
					]
				},
				{
					"bbox_id": "1583398240023-0-2",
					"contents": [
						110,
						19,
						33,
						29
					]
				},
				{
					"bbox_id": "1583398240023-0-3",
					"contents": [
						139,
						19,
						25,
						29
					]
				},
				{
					"bbox_id": "1583398240023-0-4",
					"contents": [
						170,
						19,
						36,
						29
					]
				},
				{
					"bbox_id": "1583398240023-0-7",
					"contents": [
						265,
						19,
						36,
						29
					]
				},
				{
					"bbox_id": "1583398240023-0-8",
					"contents": [
						296,
						19,
						26,
						29
					]
				},
				{
					"bbox_id": "1583398240023-0-9",
					"contents": [
						324,
						19,
						30,
						29
					]
				},
				{
					"bbox_id": "1583398240023-0-10",
					"contents": [
						351,
						19,
						25,
						29
					]
				},
				{
					"bbox_id": "1583398240023-0-11",
					"contents": [
						380,
						19,
						33,
						29
					]
				},
				{
					"bbox_id": "1583398240023-0-12",
					"contents": [
						410,
						19,
						26,
						29
					]
				},
				{
					"bbox_id": "1583398240023-0-13",
					"contents": [
						441,
						19,
						36,
						29
					]
				},
				{
					"bbox_id": "1583398240023-0-14",
					"contents": [
						472,
						19,
						26,
						29
					]
				},
				{
					"bbox_id": "1583398240023-1-0",
					"contents": [
						161,
						37,
						36,
						28
					]
				},
				{
					"bbox_id": "1583398240023-1-1",
					"contents": [
						197,
						37,
						36,
						28
					]
				},
				{
					"bbox_id": "1583398240023-1-2",
					"contents": [
						227,
						37,
						25,
						28
					]
				},
				{
					"bbox_id": "1583398240023-1-4",
					"contents": [
						284,
						37,
						36,
						28
					]
				},
				{
					"bbox_id": "1583398240023-1-6",
					"contents": [
						338,
						37,
						25,
						28
					]
				},
				{
					"bbox_id": "1583398240023-1-9",
					"contents": [
						425,
						37,
						33,
						28
					]
				},
				{
					"bbox_id": "1583398240023-1-10",
					"contents": [
						460,
						37,
						36,
						28
					]
				},
				{
					"bbox_id": "1583398240023-1-11",
					"contents": [
						494,
						37,
						32,
						28
					]
				},
				{
					"bbox_id": "1583398240023-2-0",
					"contents": [
						114,
						58,
						35,
						31
					]
				},
				{
					"bbox_id": "1583398240023-2-1",
					"contents": [
						149,
						58,
						35,
						31
					]
				},
				{
					"bbox_id": "1583398240023-2-2",
					"contents": [
						183,
						58,
						33,
						31
					]
				},
				{
					"bbox_id": "1583398240023-2-3",
					"contents": [
						218,
						58,
						36,
						31
					]
				},
				{
					"bbox_id": "1583398240023-2-4",
					"contents": [
						252,
						58,
						33,
						31
					]
				},
				{
					"bbox_id": "1583398240023-2-5",
					"contents": [
						286,
						58,
						35,
						31
					]
				},
				{
					"bbox_id": "1583398240023-2-6",
					"contents": [
						322,
						58,
						36,
						31
					]
				},
				{
					"bbox_id": "1583398240023-2-7",
					"contents": [
						356,
						58,
						33,
						31
					]
				},
				{
					"bbox_id": "1583398240023-2-8",
					"contents": [
						390,
						58,
						34,
						31
					]
				},
				{
					"bbox_id": "1583398240023-2-10",
					"contents": [
						461,
						58,
						36,
						31
					]
				},
				{
					"bbox_id": "1583398240023-2-11",
					"contents": [
						492,
						58,
						26,
						31
					]
				},
				{
					"bbox_id": "1583398240023-3-1",
					"contents": [
						182,
						75,
						30,
						24
					]
				},
				{
					"bbox_id": "1583398240023-3-2",
					"contents": [
						207,
						75,
						20,
						24
					]
				},
				{
					"bbox_id": "1583398240023-3-3",
					"contents": [
						229,
						75,
						25,
						24
					]
				},
				{
					"bbox_id": "1583398240023-3-4",
					"contents": [
						254,
						75,
						25,
						24
					]
				},
				{
					"bbox_id": "1583398240023-3-6",
					"contents": [
						299,
						75,
						22,
						24
					]
				},
				{
					"bbox_id": "1583398240023-3-7",
					"contents": [
						323,
						75,
						27,
						24
					]
				},
				{
					"bbox_id": "1583398240023-3-10",
					"contents": [
						390,
						75,
						27,
						24
					]
				},
				{
					"bbox_id": "1583398240023-3-11",
					"contents": [
						416,
						75,
						25,
						24
					]
				},
				{
					"bbox_id": "1583398240023-3-12",
					"contents": [
						442,
						75,
						27,
						24
					]
				},
				{
					"bbox_id": "1583398240023-3-13",
					"contents": [
						469,
						75,
						27,
						24
					]
				},
				{
					"bbox_id": "1583398240023-3-14",
					"contents": [
						493,
						75,
						20,
						24
					]
				},
				{
					"bbox_id": "1583398240023-4-1",
					"contents": [
						108,
						97,
						25,
						25
					]
				},
				{
					"bbox_id": "1583398240023-4-2",
					"contents": [
						136,
						97,
						30,
						25
					]
				},
				{
					"bbox_id": "1583398240023-4-3",
					"contents": [
						163,
						97,
						25,
						25
					]
				},
				{
					"bbox_id": "1583398240023-4-4",
					"contents": [
						188,
						97,
						25,
						25
					]
				},
				{
					"bbox_id": "1583398240023-4-6",
					"contents": [
						236,
						97,
						20,
						25
					]
				},
				{
					"bbox_id": "1583398240023-4-8",
					"contents": [
						277,
						97,
						21,
						25
					]
				},
				{
					"bbox_id": "1583398240023-4-9",
					"contents": [
						304,
						97,
						32,
						25
					]
				},
				{
					"bbox_id": "1583398240023-4-10",
					"contents": [
						335,
						97,
						30,
						25
					]
				},
				{
					"bbox_id": "1583398240023-4-11",
					"contents": [
						363,
						97,
						26,
						25
					]
				},
				{
					"bbox_id": "1583398240023-4-12",
					"contents": [
						389,
						97,
						27,
						25
					]
				},
				{
					"bbox_id": "1583398240023-4-14",
					"contents": [
						443,
						97,
						30,
						25
					]
				},
				{
					"bbox_id": "1583398240023-4-15",
					"contents": [
						465,
						97,
						14,
						25
					]
				},
				{
					"bbox_id": "1583398240023-5-2",
					"contents": [
						92,
						117,
						35,
						29
					]
				},
				{
					"bbox_id": "1583398240023-5-3",
					"contents": [
						128,
						117,
						36,
						29
					]
				},
				{
					"bbox_id": "1583398240023-5-4",
					"contents": [
						162,
						117,
						33,
						29
					]
				},
				{
					"bbox_id": "1583398240023-5-5",
					"contents": [
						191,
						117,
						25,
						29
					]
				},
				{
					"bbox_id": "1583398240023-5-6",
					"contents": [
						219,
						117,
						30,
						29
					]
				},
				{
					"bbox_id": "1583398240023-5-7",
					"contents": [
						246,
						117,
						24,
						29
					]
				},
				{
					"bbox_id": "1583398240023-5-9",
					"contents": [
						312,
						117,
						36,
						29
					]
				},
				{
					"bbox_id": "1583398240023-5-10",
					"contents": [
						348,
						117,
						36,
						29
					]
				},
				{
					"bbox_id": "1583398240023-5-11",
					"contents": [
						384,
						117,
						36,
						29
					]
				},
				{
					"bbox_id": "1583398240023-5-13",
					"contents": [
						455,
						117,
						34,
						29
					]
				},
				{
					"bbox_id": "1583398240023-5-14",
					"contents": [
						490,
						117,
						36,
						29
					]
				},
				{
					"bbox_id": "1583398240023-6-0",
					"contents": [
						91,
						135,
						31,
						31
					]
				},
				{
					"bbox_id": "1583398240023-6-3",
					"contents": [
						190,
						135,
						33,
						31
					]
				},
				{
					"bbox_id": "1583398240023-6-4",
					"contents": [
						219,
						135,
						25,
						31
					]
				},
				{
					"bbox_id": "1583398240023-6-6",
					"contents": [
						298,
						135,
						60,
						31
					]
				},
				{
					"bbox_id": "1583398240023-6-7",
					"contents": [
						344,
						135,
						33,
						31
					]
				},
				{
					"bbox_id": "1583398240023-6-8",
					"contents": [
						378,
						135,
						34,
						31
					]
				},
				{
					"bbox_id": "1583398240023-6-10",
					"contents": [
						457,
						135,
						60,
						31
					]
				},
				{
					"bbox_id": "1583398240023-7-0",
					"contents": [
						142,
						148,
						20,
						22
					]
				},
				{
					"bbox_id": "1583398240023-7-1",
					"contents": [
						157,
						148,
						11,
						22
					]
				},
				{
					"bbox_id": "1583398240023-7-2",
					"contents": [
						176,
						148,
						27,
						22
					]
				},
				{
					"bbox_id": "1583398240023-7-3",
					"contents": [
						202,
						148,
						25,
						22
					]
				},
				{
					"bbox_id": "1583398240023-7-5",
					"contents": [
						249,
						148,
						30,
						22
					]
				},
				{
					"bbox_id": "1583398240023-7-7",
					"contents": [
						299,
						148,
						17,
						22
					]
				},
				{
					"bbox_id": "1583398240023-7-8",
					"contents": [
						321,
						148,
						27,
						22
					]
				},
				{
					"bbox_id": "1583398240023-7-9",
					"contents": [
						347,
						148,
						25,
						22
					]
				},
				{
					"bbox_id": "1583398240023-7-10",
					"contents": [
						372,
						148,
						25,
						22
					]
				},
				{
					"bbox_id": "1583398240023-7-11",
					"contents": [
						397,
						148,
						25,
						22
					]
				},
				{
					"bbox_id": "1583398240023-7-13",
					"contents": [
						437,
						148,
						17,
						22
					]
				},
				{
					"bbox_id": "1583398240023-7-14",
					"contents": [
						459,
						148,
						27,
						22
					]
				},
				{
					"bbox_id": "1583398240023-7-15",
					"contents": [
						482,
						148,
						19,
						22
					]
				},
				{
					"bbox_id": "1583398240023-8-1",
					"contents": [
						69,
						170,
						19,
						23
					]
				},
				{
					"bbox_id": "1583398240023-8-3",
					"contents": [
						110,
						170,
						27,
						23
					]
				},
				{
					"bbox_id": "1583398240023-8-4",
					"contents": [
						139,
						170,
						30,
						23
					]
				},
				{
					"bbox_id": "1583398240023-8-5",
					"contents": [
						166,
						170,
						24,
						23
					]
				},
				{
					"bbox_id": "1583398240023-8-6",
					"contents": [
						191,
						170,
						27,
						23
					]
				},
				{
					"bbox_id": "1583398240023-8-7",
					"contents": [
						220,
						170,
						30,
						23
					]
				},
				{
					"bbox_id": "1583398240023-8-8",
					"contents": [
						247,
						170,
						24,
						23
					]
				},
				{
					"bbox_id": "1583398240023-8-11",
					"contents": [
						319,
						170,
						21,
						23
					]
				},
				{
					"bbox_id": "1583398240023-8-12",
					"contents": [
						343,
						170,
						27,
						23
					]
				},
				{
					"bbox_id": "1583398240023-8-13",
					"contents": [
						370,
						170,
						27,
						23
					]
				},
				{
					"bbox_id": "1583398240023-8-14",
					"contents": [
						394,
						170,
						21,
						23
					]
				},
				{
					"bbox_id": "1583398240023-8-15",
					"contents": [
						417,
						170,
						25,
						23
					]
				},
				{
					"bbox_id": "1583398240023-8-16",
					"contents": [
						442,
						170,
						25,
						23
					]
				},
				{
					"bbox_id": "1583398240023-8-17",
					"contents": [
						468,
						170,
						26,
						23
					]
				},
				{
					"bbox_id": "1583398240023-8-18",
					"contents": [
						494,
						170,
						27,
						23
					]
				},
				{
					"bbox_id": "1583398240023-9-2",
					"contents": [
						87,
						190,
						25,
						24
					]
				},
				{
					"bbox_id": "1583398240023-9-3",
					"contents": [
						113,
						190,
						26,
						24
					]
				},
				{
					"bbox_id": "1583398240023-9-6",
					"contents": [
						188,
						190,
						25,
						24
					]
				},
				{
					"bbox_id": "1583398240023-9-7",
					"contents": [
						213,
						190,
						25,
						24
					]
				},
				{
					"bbox_id": "1583398240023-9-8",
					"contents": [
						238,
						190,
						25,
						24
					]
				},
				{
					"bbox_id": "1583398240023-9-9",
					"contents": [
						262,
						190,
						22,
						24
					]
				},
				{
					"bbox_id": "1583398240023-9-10",
					"contents": [
						284,
						190,
						23,
						24
					]
				},
				{
					"bbox_id": "1583398240023-9-11",
					"contents": [
						301,
						190,
						11,
						24
					]
				},
				{
					"bbox_id": "1583398240023-9-13",
					"contents": [
						329,
						190,
						23,
						24
					]
				},
				{
					"bbox_id": "1583398240023-9-14",
					"contents": [
						354,
						190,
						27,
						24
					]
				},
				{
					"bbox_id": "1583398240023-9-16",
					"contents": [
						403,
						190,
						26,
						24
					]
				},
				{
					"bbox_id": "1583398240023-9-18",
					"contents": [
						452,
						190,
						21,
						24
					]
				},
				{
					"bbox_id": "1583398240023-9-19",
					"contents": [
						473,
						190,
						21,
						24
					]
				},
				{
					"bbox_id": "1583398240023-9-20",
					"contents": [
						493,
						190,
						18,
						24
					]
				},
				{
					"bbox_id": "1583398240023-10-0",
					"contents": [
						94,
						208,
						30,
						23
					]
				},
				{
					"bbox_id": "1583398240023-10-2",
					"contents": [
						138,
						208,
						19,
						23
					]
				},
				{
					"bbox_id": "1583398240023-10-3",
					"contents": [
						160,
						208,
						25,
						23
					]
				},
				{
					"bbox_id": "1583398240023-10-4",
					"contents": [
						188,
						208,
						30,
						23
					]
				},
				{
					"bbox_id": "1583398240023-10-7",
					"contents": [
						273,
						208,
						21,
						23
					]
				},
				{
					"bbox_id": "1583398240023-10-8",
					"contents": [
						295,
						208,
						23,
						23
					]
				},
				{
					"bbox_id": "1583398240023-10-9",
					"contents": [
						315,
						208,
						17,
						23
					]
				},
				{
					"bbox_id": "1583398240023-10-10",
					"contents": [
						337,
						208,
						27,
						23
					]
				},
				{
					"bbox_id": "1583398240023-10-12",
					"contents": [
						385,
						208,
						18,
						23
					]
				},
				{
					"bbox_id": "1583398240023-10-13",
					"contents": [
						403,
						208,
						19,
						23
					]
				},
				{
					"bbox_id": "1583398240023-10-14",
					"contents": [
						422,
						208,
						19,
						23
					]
				},
				{
					"bbox_id": "1583398240023-10-16",
					"contents": [
						472,
						208,
						27,
						23
					]
				},
				{
					"bbox_id": "1583398240023-10-17",
					"contents": [
						496,
						208,
						20,
						23
					]
				},
				{
					"bbox_id": "1583398240023-11-1",
					"contents": [
						145,
						226,
						21,
						23
					]
				},
				{
					"bbox_id": "1583398240023-11-2",
					"contents": [
						168,
						226,
						25,
						23
					]
				},
				{
					"bbox_id": "1583398240023-11-3",
					"contents": [
						194,
						226,
						26,
						23
					]
				},
				{
					"bbox_id": "1583398240023-11-6",
					"contents": [
						264,
						226,
						25,
						23
					]
				},
				{
					"bbox_id": "1583398240023-11-7",
					"contents": [
						287,
						226,
						20,
						23
					]
				},
				{
					"bbox_id": "1583398240023-11-9",
					"contents": [
						329,
						226,
						21,
						23
					]
				},
				{
					"bbox_id": "1583398240023-11-10",
					"contents": [
						351,
						226,
						23,
						23
					]
				},
				{
					"bbox_id": "1583398240023-12-1",
					"contents": [
						207,
						248,
						27,
						22
					]
				},
				{
					"bbox_id": "1583398240023-12-2",
					"contents": [
						231,
						248,
						20,
						22
					]
				},
				{
					"bbox_id": "1583398240023-12-7",
					"contents": [
						352,
						248,
						25,
						22
					]
				},
				{
					"bbox_id": "1583398240023-12-8",
					"contents": [
						375,
						248,
						21,
						22
					]
				},
				{
					"bbox_id": "1583398240023-12-9",
					"contents": [
						396,
						248,
						21,
						22
					]
				},
				{
					"bbox_id": "1583398240023-12-12",
					"contents": [
						476,
						248,
						30,
						22
					]
				},
				{
					"bbox_id": "1583398240023-12-13",
					"contents": [
						501,
						248,
						21,
						22
					]
				}
			]
		}
	]
}